invoiceCHIOU/__init__.py
invoiceCHIOU/invoice.py
invoiceCHIOU-0.1.0.dist-info/LICENSE
invoiceCHIOU-0.1.0.dist-info/METADATA
invoiceCHIOU-0.1.0.dist-info/WHEEL
invoiceCHIOU-0.1.0.dist-info/top_level.txt
invoiceCHIOU-0.1.0.dist-info/RECORD
