Metadata-Version: 2.1
Name: invoiceCHIOU
Version: 0.1.0
Summary: Taiwan invoice number
Home-page: https://github.com/chiou3qorz/invoiceCHIOU
Author: jeng
Author-email: chiou@e-happy.com.tw
License: UNKNOWN
Keywords: invoice
Platform: UNKNOWN
Classifier: Programming Language :: Python :: 3
Classifier: License :: OSI Approved :: MIT License
